{
    "os": "macOS-14.0-arm64-arm-64bit",
    "python": "3.11.5",
    "heartbeatAt": "2023-10-24T18:32:38.808276",
    "startedAt": "2023-10-24T18:32:38.213366",
    "docker": null,
    "cuda": null,
    "args": [],
    "state": "running",
    "program": "Text_Summarization_with_Transformers/BART_transformer_summarization_enhanced.ipynb",
    "codePathLocal": null,
    "root": "/Users/nigoo/Documents/Code/My_GitHub_Repositories",
    "host": "fermi_framework",
    "username": "ahmedelnagar",
    "executable": "/Users/nigoo/anaconda3/bin/python",
    "cpu_count": 8,
    "cpu_count_logical": 8,
    "disk": {
        "/": {
            "total": 460.4317207336426,
            "used": 251.797607421875
        }
    },
    "gpuapple": {
        "type": "arm",
        "vendor": "Apple"
    },
    "memory": {
        "total": 16.0
    }
}
